quafel/__init__.py
quafel/__main__.py
quafel/cli.py
quafel/hooks.py
quafel/pipeline_registry.py
quafel/pipelines/__init__.py
quafel/pipelines/data_generation/__init__.py
quafel/pipelines/data_generation/nodes.py
quafel/pipelines/data_generation/pipeline.py
quafel/pipelines/data_science/__init__.py
quafel/pipelines/data_science/frameworks.py
quafel/pipelines/data_science/nodes.py
quafel/pipelines/data_science/pipeline.py
quafel/pipelines/visualization/README.md
quafel/pipelines/visualization/__init__.py
quafel/pipelines/visualization/nodes.py
quafel/pipelines/visualization/pipeline.py
quafel/runner/__init__.py
quafel/runner/dask_runner.py
quafel/runner/parallel_runner.py
quafel/settings.py
quafel-0.1.0.dist-info/LICENSE
quafel-0.1.0.dist-info/METADATA
quafel-0.1.0.dist-info/WHEEL
quafel-0.1.0.dist-info/RECORD
