Metadata-Version: 2.1
Name: quafel
Version: 0.1.0
Summary: 
Author: lc3267
Author-email: melvin.strobl@kit.edu
Requires-Python: >=3.10,<3.12
Classifier: Programming Language :: Python :: 3
Classifier: Programming Language :: Python :: 3.10
Classifier: Programming Language :: Python :: 3.11
Requires-Dist: bokeh (>=3.3.0,<4.0.0)
Requires-Dist: cirq (>=1.2.0,<2.0.0)
Requires-Dist: distributed (>=2023.10.0,<2024.0.0)
Requires-Dist: jax (>=0.4.25,<0.5.0)
Requires-Dist: jaxlib (>=0.4.25,<0.5.0)
Requires-Dist: kaleido (==0.2.1)
Requires-Dist: kedro (>=0.18.13,<0.19.0)
Requires-Dist: kedro-viz (==6.6.0)
Requires-Dist: pennylane (>=0.33.1,<0.34.0)
Requires-Dist: pennylane-qiskit (>=0.32.0,<0.33.0)
Requires-Dist: plotly (>=5.18.0,<6.0.0)
Requires-Dist: qibo (>=0.2.2,<0.3.0)
Requires-Dist: qiskit (>=0.45.0,<0.46.0)
Requires-Dist: qrisp (>=0.3.0,<0.4.0)
Requires-Dist: qulacs (>=0.6.2,<0.7.0)
